<?xml version="1.0" encoding="utf-8" ?>
<dwsync>
<file name="basic.js" server="C:/xampp/htdocs/noworries/" local="130801563780000000" remote="130801563780000000" Dst="2" />
<file name="brainfuck.js" server="C:/xampp/htdocs/noworries/" local="130801563780000000" remote="130801563780000000" Dst="2" />
<file name="c.js" server="C:/xampp/htdocs/noworries/" local="130801563780000000" remote="130801563780000000" Dst="2" />
<file name="coldfusion.js" server="C:/xampp/htdocs/noworries/" local="130801563780000000" remote="130801563780000000" Dst="2" />
<file name="cpp.js" server="C:/xampp/htdocs/noworries/" local="130801563780000000" remote="130801563780000000" Dst="2" />
<file name="css.js" server="C:/xampp/htdocs/noworries/" local="130801563780000000" remote="130801563780000000" Dst="2" />
<file name="html.js" server="C:/xampp/htdocs/noworries/" local="130801563780000000" remote="130801563780000000" Dst="2" />
<file name="java.js" server="C:/xampp/htdocs/noworries/" local="130801563780000000" remote="130801563780000000" Dst="2" />
<file name="js.js" server="C:/xampp/htdocs/noworries/" local="130801563780000000" remote="130801563780000000" Dst="2" />
<file name="pas.js" server="C:/xampp/htdocs/noworries/" local="130801563780000000" remote="130801563780000000" Dst="2" />
<file name="perl.js" server="C:/xampp/htdocs/noworries/" local="130801563780000000" remote="130801563780000000" Dst="2" />
<file name="php.js" server="C:/xampp/htdocs/noworries/" local="130801563780000000" remote="130801563780000000" Dst="2" />
<file name="phtml.js" server="C:/xampp/htdocs/noworries/" local="130801563780000000" remote="130801563780000000" Dst="2" />
<file name="python.js" server="C:/xampp/htdocs/noworries/" local="130801563780000000" remote="130801563780000000" Dst="2" />
<file name="robotstxt.js" server="C:/xampp/htdocs/noworries/" local="130801563780000000" remote="130801563780000000" Dst="2" />
<file name="ruby.js" server="C:/xampp/htdocs/noworries/" local="130801563780000000" remote="130801563780000000" Dst="2" />
<file name="sql.js" server="C:/xampp/htdocs/noworries/" local="130801563780000000" remote="130801563780000000" Dst="2" />
<file name="tsql.js" server="C:/xampp/htdocs/noworries/" local="130801563780000000" remote="130801563780000000" Dst="2" />
<file name="vb.js" server="C:/xampp/htdocs/noworries/" local="130801563780000000" remote="130801563780000000" Dst="2" />
<file name="xml.js" server="C:/xampp/htdocs/noworries/" local="130801563780000000" remote="130801563780000000" Dst="2" />
</dwsync>