<?xml version="1.0" encoding="utf-8" ?>
<dwsync>
<file name="Assertion.php" server="C:/xampp/htdocs/noworries/" local="130801570520000000" remote="130801570520000000" Dst="2" />
<file name="Element.php" server="C:/xampp/htdocs/noworries/" local="130801570520000000" remote="130801570520000000" Dst="2" />
<file name="EncryptedData.php" server="C:/xampp/htdocs/noworries/" local="130801570520000000" remote="130801570520000000" Dst="2" />
<file name="EncryptedKey.php" server="C:/xampp/htdocs/noworries/" local="130801570520000000" remote="130801570520000000" Dst="2" />
<file name="Exception.php" server="C:/xampp/htdocs/noworries/" local="130801570520000000" remote="130801570520000000" Dst="2" />
<file name="KeyInfo.php" server="C:/xampp/htdocs/noworries/" local="130801570520000000" remote="130801570520000000" Dst="2" />
<file name="Security.php" server="C:/xampp/htdocs/noworries/" local="130801570520000000" remote="130801570520000000" Dst="2" />
<file name="SecurityTokenReference.php" server="C:/xampp/htdocs/noworries/" local="130801570520000000" remote="130801570520000000" Dst="2" />
</dwsync>