<?xml version="1.0" encoding="utf-8" ?>
<dwsync>
<file name="accordion_open.png" server="C:/xampp/htdocs/noworries/" local="130801571220000000" remote="130801571220000000" Dst="2" />
<file name="accordion_open_android.png" server="C:/xampp/htdocs/noworries/" local="130801571220000000" remote="130801571220000000" Dst="2" />
<file name="accordion_open_android_l.png" server="C:/xampp/htdocs/noworries/" local="130801571220000000" remote="130801571220000000" Dst="2" />
<file name="accordion_open_android_p.png" server="C:/xampp/htdocs/noworries/" local="130801571220000000" remote="130801571220000000" Dst="2" />
<file name="accordion_open_ipad_l.png" server="C:/xampp/htdocs/noworries/" local="130801571220000000" remote="130801571220000000" Dst="2" />
<file name="accordion_open_ipad_p.png" server="C:/xampp/htdocs/noworries/" local="130801571220000000" remote="130801571220000000" Dst="2" />
<file name="banner_1_2.png" server="C:/xampp/htdocs/noworries/" local="130801571220000000" remote="130801571220000000" Dst="2" />
<file name="banner_android.png" server="C:/xampp/htdocs/noworries/" local="130801571220000000" remote="130801571220000000" Dst="2" />
<file name="banner_ipad.png" server="C:/xampp/htdocs/noworries/" local="130801571220000000" remote="130801571220000000" Dst="2" />
<file name="banner_ipad_l.png" server="C:/xampp/htdocs/noworries/" local="130801571220000000" remote="130801571220000000" Dst="2" />
<file name="smallIcon_1_6.png" server="C:/xampp/htdocs/noworries/" local="130801571220000000" remote="130801571220000000" Dst="2" />
</dwsync>