<?xml version="1.0" encoding="utf-8" ?>
<dwsync>
<file name="install-1.6.0.0.php" server="C:/xampp/htdocs/noworries/" local="130801563140000000" remote="130801563140000000" Dst="2" />
<file name="mysql4-install-0.1.php" server="C:/xampp/htdocs/noworries/" local="130801563140000000" remote="130801563140000000" Dst="2" />
<file name="mysql4-upgrade-0.1-0.2.php" server="C:/xampp/htdocs/noworries/" local="130801563140000000" remote="130801563140000000" Dst="2" />
<file name="mysql4-upgrade-0.10-0.11.php" server="C:/xampp/htdocs/noworries/" local="130801563140000000" remote="130801563140000000" Dst="2" />
<file name="mysql4-upgrade-0.11-0.12.php" server="C:/xampp/htdocs/noworries/" local="130801563140000000" remote="130801563140000000" Dst="2" />
<file name="mysql4-upgrade-0.12-0.13.php" server="C:/xampp/htdocs/noworries/" local="130801563140000000" remote="130801563140000000" Dst="2" />
<file name="mysql4-upgrade-0.2-0.3.php" server="C:/xampp/htdocs/noworries/" local="130801563140000000" remote="130801563140000000" Dst="2" />
<file name="mysql4-upgrade-0.3-0.4.php" server="C:/xampp/htdocs/noworries/" local="130801563140000000" remote="130801563140000000" Dst="2" />
<file name="mysql4-upgrade-0.4-0.5.php" server="C:/xampp/htdocs/noworries/" local="130801563140000000" remote="130801563140000000" Dst="2" />
<file name="mysql4-upgrade-0.5-0.6.php" server="C:/xampp/htdocs/noworries/" local="130801563140000000" remote="130801563140000000" Dst="2" />
<file name="mysql4-upgrade-0.6-0.7.php" server="C:/xampp/htdocs/noworries/" local="130801563140000000" remote="130801563140000000" Dst="2" />
<file name="mysql4-upgrade-0.7-0.8.php" server="C:/xampp/htdocs/noworries/" local="130801563140000000" remote="130801563140000000" Dst="2" />
<file name="mysql4-upgrade-0.8-0.9.php" server="C:/xampp/htdocs/noworries/" local="130801563140000000" remote="130801563140000000" Dst="2" />
<file name="mysql4-upgrade-0.9-0.10.php" server="C:/xampp/htdocs/noworries/" local="130801563140000000" remote="130801563140000000" Dst="2" />
<file name="mysql4-upgrade-1.5.9.9-1.6.0.0.php" server="C:/xampp/htdocs/noworries/" local="130801563140000000" remote="130801563140000000" Dst="2" />
</dwsync>